shaurya/__init__.py
shaurya/face.py
shaurya/main.py
shaurya/tests.py
shaurya/virus.py
shaurya-2.1.3.3.dist-info/METADATA
shaurya-2.1.3.3.dist-info/WHEEL
shaurya-2.1.3.3.dist-info/top_level.txt
shaurya-2.1.3.3.dist-info/RECORD
