Metadata-Version: 2.1
Name: shaurya
Version: 2.1.3.3
Summary: my package.
Home-page: UNKNOWN
Author: Shaurya Pratap Singh
Author-email: djangokidrox21@gmail.com
License: GPL
Platform: UNKNOWN
Requires-Dist: requests
Requires-Dist: opencv-python
